Metadata-Version: 2.1
Name: event-timer
Version: 1.0.9
Summary: A event countdown manager
Home-page: https://github.com/machinexa2/EventTimer
Author: Machine Yadav
Author-email: machinexa@gmail.com
License: MIT
Download-URL: https://github.com/machinexa2/EventTimer/archive/refs/tags/v1.0.6.tar.gz
Keywords: event,config,automatic,tools
Platform: UNKNOWN
Classifier: Programming Language :: Python :: 3
Classifier: License :: OSI Approved :: MIT License
Classifier: Operating System :: OS Independent
Requires-Python: >=3.8
